npcsimulator/__init__.py
npcsimulator/centroids.py
npcsimulator/emitters.py
npcsimulator/plot.py
npcsimulator/structure_parsing.py
npcsimulator/templates.py
npcsimulator-1.0.9.dist-info/licenses/LICENCE
npcsimulator-1.0.9.dist-info/METADATA
npcsimulator-1.0.9.dist-info/WHEEL
npcsimulator-1.0.9.dist-info/top_level.txt
npcsimulator-1.0.9.dist-info/RECORD
