Metadata-Version: 2.4
Name: npcsimulator
Version: 1.0.9
Summary: Python based simulator for generating MINFLUX-like Nuclear Pore Complex data.
Author-email: Jack Peyton <jpeyton01@qub.ac.uk>
Project-URL: Homepage, https://github.com/j-peyton/NPCPackage
Project-URL: Issues, https://github.com/j-peyton/NPCPackage/issues
Classifier: Programming Language :: Python :: 3
Classifier: License :: OSI Approved :: MIT License
Classifier: Operating System :: OS Independent
Requires-Python: >=3.8
License-File: LICENCE
Dynamic: license-file
